<?xml version="1.0" ?>
<Gesture Name="left_curly_bracket05" Subject="1" Speed="fast" Number="1" NumPts="235" Millseconds="547" AppName="Gestures" AppVer="3.5.0.0" Date="Monday, March 05, 2007" TimeOfDay="5:05:00 PM">
  <Point X="814" Y="619" T="0"/>
  <Point X="813" Y="619" T="1"/>
  <Point X="812" Y="619" T="2"/>
  <Point X="811" Y="619" T="3"/>
  <Point X="810" Y="619" T="4"/>
  <Point X="808" Y="619" T="5"/>
  <Point X="806" Y="619" T="6"/>
  <Point X="804" Y="619" T="7"/>
  <Point X="801" Y="619" T="8"/>
  <Point X="798" Y="619" T="9"/>
  <Point X="794" Y="619" T="10"/>
  <Point X="791" Y="619" T="11"/>
  <Point X="786" Y="619" T="12"/>
  <Point X="782" Y="619" T="13"/>
  <Point X="778" Y="619" T="14"/>
  <Point X="773" Y="619" T="15"/>
  <Point X="769" Y="619" T="16"/>
  <Point X="768" Y="619" T="17"/>
  <Point X="765" Y="619" T="18"/>
  <Point X="762" Y="619" T="19"/>
  <Point X="761" Y="619" T="20"/>
  <Point X="760" Y="619" T="21"/>
  <Point X="759" Y="619" T="22"/>
  <Point X="758" Y="619" T="23"/>
  <Point X="757" Y="619" T="24"/>
  <Point X="757" Y="618" T="25"/>
  <Point X="757" Y="617" T="26"/>
  <Point X="756" Y="616" T="27"/>
  <Point X="756" Y="615" T="28"/>
  <Point X="756" Y="614" T="29"/>
  <Point X="755" Y="613" T="30"/>
  <Point X="755" Y="612" T="31"/>
  <Point X="754" Y="611" T="32"/>
  <Point X="754" Y="610" T="33"/>
  <Point X="752" Y="606" T="34"/>
  <Point X="751" Y="604" T="35"/>
  <Point X="750" Y="602" T="36"/>
  <Point X="749" Y="600" T="37"/>
  <Point X="748" Y="597" T="38"/>
  <Point X="746" Y="596" T="39"/>
  <Point X="745" Y="594" T="40"/>
  <Point X="744" Y="591" T="41"/>
  <Point X="743" Y="589" T="42"/>
  <Point X="742" Y="586" T="43"/>
  <Point X="741" Y="582" T="44"/>
  <Point X="739" Y="580" T="45"/>
  <Point X="739" Y="577" T="46"/>
  <Point X="738" Y="575" T="47"/>
  <Point X="737" Y="574" T="48"/>
  <Point X="737" Y="571" T="49"/>
  <Point X="736" Y="569" T="50"/>
  <Point X="735" Y="566" T="51"/>
  <Point X="735" Y="564" T="52"/>
  <Point X="734" Y="562" T="53"/>
  <Point X="734" Y="560" T="54"/>
  <Point X="734" Y="558" T="55"/>
  <Point X="733" Y="556" T="56"/>
  <Point X="733" Y="554" T="57"/>
  <Point X="733" Y="553" T="58"/>
  <Point X="733" Y="551" T="59"/>
  <Point X="732" Y="550" T="60"/>
  <Point X="732" Y="548" T="61"/>
  <Point X="732" Y="547" T="62"/>
  <Point X="732" Y="545" T="63"/>
  <Point X="732" Y="544" T="64"/>
  <Point X="732" Y="542" T="65"/>
  <Point X="732" Y="541" T="66"/>
  <Point X="732" Y="539" T="67"/>
  <Point X="732" Y="538" T="68"/>
  <Point X="731" Y="536" T="69"/>
  <Point X="731" Y="535" T="70"/>
  <Point X="731" Y="533" T="71"/>
  <Point X="731" Y="531" T="72"/>
  <Point X="730" Y="530" T="73"/>
  <Point X="730" Y="528" T="74"/>
  <Point X="729" Y="526" T="75"/>
  <Point X="729" Y="525" T="76"/>
  <Point X="728" Y="524" T="77"/>
  <Point X="728" Y="522" T="78"/>
  <Point X="726" Y="521" T="79"/>
  <Point X="726" Y="520" T="80"/>
  <Point X="725" Y="519" T="81"/>
  <Point X="724" Y="518" T="82"/>
  <Point X="723" Y="517" T="83"/>
  <Point X="721" Y="515" T="84"/>
  <Point X="719" Y="514" T="85"/>
  <Point X="717" Y="513" T="86"/>
  <Point X="715" Y="512" T="87"/>
  <Point X="712" Y="511" T="88"/>
  <Point X="710" Y="509" T="89"/>
  <Point X="707" Y="508" T="90"/>
  <Point X="704" Y="507" T="91"/>
  <Point X="702" Y="507" T="92"/>
  <Point X="700" Y="506" T="93"/>
  <Point X="697" Y="505" T="94"/>
  <Point X="694" Y="505" T="95"/>
  <Point X="692" Y="504" T="96"/>
  <Point X="691" Y="503" T="97"/>
  <Point X="689" Y="503" T="98"/>
  <Point X="688" Y="503" T="99"/>
  <Point X="687" Y="503" T="100"/>
  <Point X="686" Y="503" T="101"/>
  <Point X="685" Y="503" T="102"/>
  <Point X="684" Y="503" T="103"/>
  <Point X="684" Y="503" T="104"/>
  <Point X="684" Y="503" T="105"/>
  <Point X="683" Y="503" T="106"/>
  <Point X="683" Y="504" T="107"/>
  <Point X="683" Y="504" T="108"/>
  <Point X="683" Y="505" T="109"/>
  <Point X="683" Y="506" T="110"/>
  <Point X="683" Y="506" T="111"/>
  <Point X="683" Y="506" T="112"/>
  <Point X="683" Y="507" T="113"/>
  <Point X="683" Y="507" T="114"/>
  <Point X="683" Y="507" T="115"/>
  <Point X="684" Y="507" T="116"/>
  <Point X="684" Y="507" T="117"/>
  <Point X="685" Y="507" T="118"/>
  <Point X="685" Y="507" T="119"/>
  <Point X="686" Y="507" T="120"/>
  <Point X="687" Y="507" T="121"/>
  <Point X="687" Y="507" T="122"/>
  <Point X="688" Y="507" T="123"/>
  <Point X="689" Y="507" T="124"/>
  <Point X="690" Y="507" T="125"/>
  <Point X="691" Y="507" T="126"/>
  <Point X="692" Y="507" T="127"/>
  <Point X="693" Y="507" T="128"/>
  <Point X="694" Y="507" T="129"/>
  <Point X="695" Y="507" T="130"/>
  <Point X="696" Y="507" T="131"/>
  <Point X="697" Y="507" T="132"/>
  <Point X="699" Y="507" T="133"/>
  <Point X="700" Y="507" T="134"/>
  <Point X="702" Y="507" T="135"/>
  <Point X="704" Y="507" T="136"/>
  <Point X="705" Y="507" T="137"/>
  <Point X="707" Y="507" T="138"/>
  <Point X="709" Y="507" T="139"/>
  <Point X="711" Y="507" T="140"/>
  <Point X="712" Y="506" T="141"/>
  <Point X="714" Y="506" T="142"/>
  <Point X="716" Y="506" T="143"/>
  <Point X="717" Y="505" T="144"/>
  <Point X="718" Y="504" T="145"/>
  <Point X="720" Y="503" T="146"/>
  <Point X="721" Y="502" T="147"/>
  <Point X="722" Y="502" T="148"/>
  <Point X="722" Y="501" T="149"/>
  <Point X="723" Y="500" T="150"/>
  <Point X="724" Y="498" T="151"/>
  <Point X="724" Y="498" T="152"/>
  <Point X="725" Y="497" T="153"/>
  <Point X="725" Y="496" T="154"/>
  <Point X="725" Y="495" T="155"/>
  <Point X="726" Y="495" T="156"/>
  <Point X="726" Y="494" T="157"/>
  <Point X="727" Y="493" T="158"/>
  <Point X="727" Y="491" T="159"/>
  <Point X="728" Y="489" T="160"/>
  <Point X="729" Y="488" T="161"/>
  <Point X="730" Y="485" T="162"/>
  <Point X="730" Y="483" T="163"/>
  <Point X="731" Y="480" T="164"/>
  <Point X="732" Y="479" T="165"/>
  <Point X="732" Y="476" T="166"/>
  <Point X="733" Y="473" T="167"/>
  <Point X="734" Y="471" T="168"/>
  <Point X="734" Y="468" T="169"/>
  <Point X="735" Y="464" T="170"/>
  <Point X="736" Y="462" T="171"/>
  <Point X="736" Y="460" T="172"/>
  <Point X="736" Y="457" T="173"/>
  <Point X="737" Y="455" T="174"/>
  <Point X="737" Y="453" T="175"/>
  <Point X="738" Y="451" T="176"/>
  <Point X="738" Y="449" T="177"/>
  <Point X="738" Y="448" T="178"/>
  <Point X="739" Y="447" T="179"/>
  <Point X="739" Y="445" T="180"/>
  <Point X="739" Y="444" T="181"/>
  <Point X="740" Y="444" T="182"/>
  <Point X="740" Y="443" T="183"/>
  <Point X="740" Y="442" T="184"/>
  <Point X="741" Y="441" T="185"/>
  <Point X="742" Y="440" T="186"/>
  <Point X="743" Y="439" T="187"/>
  <Point X="745" Y="437" T="188"/>
  <Point X="746" Y="436" T="189"/>
  <Point X="748" Y="434" T="190"/>
  <Point X="750" Y="432" T="191"/>
  <Point X="753" Y="430" T="192"/>
  <Point X="756" Y="427" T="193"/>
  <Point X="759" Y="424" T="194"/>
  <Point X="763" Y="421" T="195"/>
  <Point X="767" Y="418" T="196"/>
  <Point X="770" Y="416" T="197"/>
  <Point X="774" Y="413" T="198"/>
  <Point X="775" Y="413" T="199"/>
  <Point X="779" Y="411" T="200"/>
  <Point X="781" Y="409" T="201"/>
  <Point X="784" Y="408" T="202"/>
  <Point X="785" Y="408" T="203"/>
  <Point X="788" Y="407" T="204"/>
  <Point X="790" Y="406" T="205"/>
  <Point X="792" Y="406" T="206"/>
  <Point X="794" Y="406" T="207"/>
  <Point X="796" Y="406" T="208"/>
  <Point X="798" Y="406" T="209"/>
  <Point X="800" Y="406" T="210"/>
  <Point X="802" Y="406" T="211"/>
  <Point X="804" Y="406" T="212"/>
  <Point X="807" Y="406" T="213"/>
  <Point X="808" Y="406" T="214"/>
  <Point X="811" Y="406" T="215"/>
  <Point X="814" Y="406" T="216"/>
  <Point X="815" Y="406" T="217"/>
  <Point X="818" Y="406" T="218"/>
  <Point X="820" Y="406" T="219"/>
  <Point X="821" Y="406" T="220"/>
  <Point X="823" Y="406" T="221"/>
  <Point X="824" Y="406" T="222"/>
  <Point X="824" Y="406" T="223"/>
  <Point X="825" Y="406" T="224"/>
  <Point X="825" Y="406" T="225"/>
  <Point X="826" Y="407" T="226"/>
  <Point X="826" Y="407" T="227"/>
  <Point X="826" Y="407" T="228"/>
  <Point X="826" Y="408" T="229"/>
  <Point X="827" Y="408" T="230"/>
  <Point X="828" Y="409" T="231"/>
  <Point X="829" Y="409" T="232"/>
  <Point X="830" Y="410" T="233"/>
  <Point X="831" Y="410" T="234"/>
</Gesture>
