<?xml version='1.0' encoding='utf-8'?>
<Gesture Name="triangle04" Subject="0" Speed="medium" Number="4" NumPts="48" Millseconds="3038" AppName="emmas_app" AppVer="1.0" Date="Monday, June 17, 2024" TimeOfDay="08:01:06 PM"><Point X="291" Y="190" T="1718647263.3446999" /><Point X="291" Y="190" T="29" /><Point X="288" Y="198" T="90" /><Point X="276" Y="221" T="140" /><Point X="246" Y="265" T="215" /><Point X="226" Y="292" T="257" /><Point X="213" Y="311" T="334" /><Point X="209" Y="318" T="390" /><Point X="204" Y="328" T="456" /><Point X="202" Y="332" T="524" /><Point X="202" Y="332" T="603" /><Point X="218" Y="338" T="656" /><Point X="229" Y="339" T="721" /><Point X="229" Y="339" T="788" /><Point X="242" Y="339" T="854" /><Point X="263" Y="340" T="907" /><Point X="304" Y="344" T="973" /><Point X="319" Y="344" T="1040" /><Point X="324" Y="344" T="1123" /><Point X="334" Y="343" T="1191" /><Point X="341" Y="343" T="1257" /><Point X="351" Y="342" T="1307" /><Point X="383" Y="347" T="1391" /><Point X="391" Y="349" T="1440" /><Point X="396" Y="350" T="1526" /><Point X="403" Y="352" T="1574" /><Point X="408" Y="353" T="1662" /><Point X="408" Y="353" T="1707" /><Point X="407" Y="348" T="1813" /><Point X="400" Y="333" T="1858" /><Point X="388" Y="313" T="1898" /><Point X="378" Y="299" T="1962" /><Point X="365" Y="280" T="2007" /><Point X="358" Y="267" T="2097" /><Point X="353" Y="258" T="2164" /><Point X="347" Y="245" T="2231" /><Point X="340" Y="229" T="2273" /><Point X="335" Y="221" T="2367" /><Point X="327" Y="210" T="2432" /><Point X="325" Y="206" T="2473" /><Point X="319" Y="199" T="2568" /><Point X="313" Y="191" T="2635" /><Point X="310" Y="187" T="2702" /><Point X="307" Y="181" T="2770" /><Point X="305" Y="178" T="2806" /><Point X="304" Y="177" T="2903" /><Point X="304" Y="177" T="2940" /><Point X="304" Y="177" T="3037" /></Gesture>