<?xml version='1.0' encoding='utf-8'?>
<Gesture Name="zig-zag08" Subject="0" Speed="medium" Number="8" NumPts="35" Millseconds="2152" AppName="emmas_app" AppVer="1.0" Date="Monday, June 17, 2024" TimeOfDay="08:53:43 PM"><Point X="105" Y="360" T="1718650420.994362" /><Point X="105" Y="360" T="26" /><Point X="105" Y="360" T="93" /><Point X="111" Y="350" T="143" /><Point X="144" Y="313" T="202" /><Point X="187" Y="266" T="260" /><Point X="193" Y="261" T="310" /><Point X="194" Y="262" T="360" /><Point X="203" Y="276" T="438" /><Point X="230" Y="308" T="505" /><Point X="255" Y="336" T="560" /><Point X="267" Y="350" T="626" /><Point X="272" Y="354" T="690" /><Point X="274" Y="355" T="758" /><Point X="275" Y="351" T="793" /><Point X="299" Y="310" T="861" /><Point X="341" Y="258" T="946" /><Point X="346" Y="252" T="993" /><Point X="347" Y="253" T="1060" /><Point X="357" Y="265" T="1126" /><Point X="384" Y="289" T="1213" /><Point X="406" Y="310" T="1260" /><Point X="417" Y="323" T="1348" /><Point X="428" Y="335" T="1393" /><Point X="436" Y="345" T="1460" /><Point X="439" Y="348" T="1526" /><Point X="440" Y="348" T="1593" /><Point X="441" Y="347" T="1682" /><Point X="451" Y="331" T="1749" /><Point X="491" Y="290" T="1793" /><Point X="508" Y="267" T="1884" /><Point X="511" Y="263" T="1950" /><Point X="513" Y="259" T="1993" /><Point X="513" Y="259" T="2085" /><Point X="513" Y="259" T="2126" /></Gesture>